envoy/__init__.py
envoy/admin/__init__.py
envoy/admin/v2alpha/__init__.py
envoy/admin/v2alpha/certs_pb2.py
envoy/admin/v2alpha/clusters_pb2.py
envoy/admin/v2alpha/config_dump_pb2.py
envoy/admin/v2alpha/listeners_pb2.py
envoy/admin/v2alpha/memory_pb2.py
envoy/admin/v2alpha/metrics_pb2.py
envoy/admin/v2alpha/mutex_stats_pb2.py
envoy/admin/v2alpha/server_info_pb2.py
envoy/admin/v2alpha/tap_pb2.py
envoy/admin/v3/__init__.py
envoy/admin/v3/certs_pb2.py
envoy/admin/v3/clusters_pb2.py
envoy/admin/v3/config_dump_pb2.py
envoy/admin/v3/config_dump_shared_pb2.py
envoy/admin/v3/init_dump_pb2.py
envoy/admin/v3/listeners_pb2.py
envoy/admin/v3/memory_pb2.py
envoy/admin/v3/metrics_pb2.py
envoy/admin/v3/mutex_stats_pb2.py
envoy/admin/v3/server_info_pb2.py
envoy/admin/v3/tap_pb2.py
envoy/annotations/__init__.py
envoy/annotations/deprecation_pb2.py
envoy/annotations/resource_pb2.py
envoy/api/__init__.py
envoy/api/v2/__init__.py
envoy/api/v2/cds_pb2.py
envoy/api/v2/cluster_pb2.py
envoy/api/v2/discovery_pb2.py
envoy/api/v2/eds_pb2.py
envoy/api/v2/endpoint_pb2.py
envoy/api/v2/lds_pb2.py
envoy/api/v2/listener_pb2.py
envoy/api/v2/rds_pb2.py
envoy/api/v2/route_pb2.py
envoy/api/v2/scoped_route_pb2.py
envoy/api/v2/srds_pb2.py
envoy/api/v2/auth/__init__.py
envoy/api/v2/auth/cert_pb2.py
envoy/api/v2/auth/common_pb2.py
envoy/api/v2/auth/secret_pb2.py
envoy/api/v2/auth/tls_pb2.py
envoy/api/v2/cluster/__init__.py
envoy/api/v2/cluster/circuit_breaker_pb2.py
envoy/api/v2/cluster/filter_pb2.py
envoy/api/v2/cluster/outlier_detection_pb2.py
envoy/api/v2/core/__init__.py
envoy/api/v2/core/address_pb2.py
envoy/api/v2/core/backoff_pb2.py
envoy/api/v2/core/base_pb2.py
envoy/api/v2/core/config_source_pb2.py
envoy/api/v2/core/event_service_config_pb2.py
envoy/api/v2/core/grpc_method_list_pb2.py
envoy/api/v2/core/grpc_service_pb2.py
envoy/api/v2/core/health_check_pb2.py
envoy/api/v2/core/http_uri_pb2.py
envoy/api/v2/core/protocol_pb2.py
envoy/api/v2/core/socket_option_pb2.py
envoy/api/v2/endpoint/__init__.py
xds_protos-1.76.0.dist-info/METADATA
xds_protos-1.76.0.dist-info/WHEEL
xds_protos-1.76.0.dist-info/top_level.txt
xds_protos-1.76.0.dist-info/RECORD
