Metadata-Version: 2.1
Name: xds-protos
Version: 1.76.0
Summary: Generated Python code from envoyproxy/data-plane-api
Home-page: https://grpc.io
Author: The gRPC Authors
Author-email: grpc-io@googlegroups.com
License: Apache License 2.0
Classifier: Development Status :: 3 - Alpha
Classifier: Programming Language :: Python
Classifier: Programming Language :: Python :: 3
Classifier: License :: OSI Approved :: Apache Software License
Requires-Python: >=3.9
Requires-Dist: grpcio >=1.74.0
Requires-Dist: protobuf <7.0.0,>=6.31.1
